{
	"education": [
		{
			"institute": "Malta College for Arts, Science and Technology (MCAST)",
			"website": "https://mcast.edu.mt",
			"location": "Paola, Malta",
			"course": "Bachelor of Science (Honours) in Software Development",
			"startDate": "2021",
			"endDate": "2024",
			"description": "Focuses on creating software applications using formal design patterns, and solving complex real-world problems using formal methodologies. Includes units such as secure software development, server-side and client-side scripting, discrete mathematics, and other similar modules.",
			"bullets": [],
			"technologies": [
				"JavaScript",
				"Angular",
				"Bootstrap",

				"Java",
				"Selenium",

				"RESTful API",
				"C#",
				"ASP.NET Core",

				"Android Studio",
				"Firebase",

				"Amazon Web Services",
				"Google Cloud",

				"Algorithms",
				"Data Structures",

				"OWASP ZAP",

				"C",
				"Python",
				"R",

				"RStudio",

				"TensorFlow",
				"Keras",
				"Roboflow",
				"YOLOv8",
				"NumPy",
				"Pandas",
				"OpenCV",

				"Docker",
				"Postman",
				"Redis",

				"LaTeX",

				"SQL",
				"SQL Data Modeller",
				"SQL Server Management Studio",
				"MongoDB",
				"Power BI",

				"CakePHP",
				"PHP",
				"XAMPP"
			]
		},
		{
			"institute": "Malta College for Arts, Science and Technology (MCAST)",
			"website": "https://mcast.edu.mt",
			"location": "Paola, Malta",
			"course": "Advanced Diploma in IT (Multimedia Software Development)",
			"startDate": "2019",
			"endDate": "2021",
			"description": "Focuses on software development skills along with the necessary knowledge for multimedia artefact development, manipulation and integration. Includes units such as game development, mobile application development, database design, website development, and other similar modules.",
			"bullets": [],
			"technologies": [
				"Python",
				"OpenCV",

				"ThingSpeak IoT",

				"Fritzing",
				"Raspberry Pi",

				"Construct 2",
				"Lua",
				"Unity",

				"Cordova",
				"Ionic",

				"HTML",
				"CSS",
				"JavaScript",
				"jQuery",

				"C#",
				"ASP.NET Core",

				"SQL",
				"SQL Data Modeller",
				"SQL Server Management Studio",

				"Statistics",
				"Game Theory",

				"Cisco Packet Tracer",
				"Wireshark",

				"Adobe Illustrator",
				"Adobe Photoshop",
				"Adobe After Effects",
				"Adobe Premier Pro",

				"Audacity",

				"WebVR",
				"A-Frame"
			]
		},
		{
			"institute": "Giovanni Curmi Higher Secondary School (GCHSS)",
			"website": "http://gchss.edu.mt",
			"location": "Naxxar, Malta",
			"course": "Post Secondary (MATSEC)",
			"startDate": "2016",
			"endDate": "2019",
			"description": "",
			"bullets": [
				"A Levels - Computing, Pure Maths",
				"Intermediates - Physics, Marketing, English, System Of Knowledge"
			],
			"technologies": []
		},
		{
			"institute": "St Aloysius College",
			"website": "https://staloysius.edu.mt",
			"location": "Birkirkara, Malta",
			"course": "Secondary School",
			"startDate": "2011",
			"endDate": "2016",
			"description": "",
			"bullets": [
				"O Levels - Maltese, English, Maths, Religion, Physics, Computer Studies, Graphical Communication, and ECDL Standard Level"
			],
			"technologies": []
		}
	]
}
